pulumi_databricks/__init__.py
pulumi_databricks/_inputs.py
pulumi_databricks/_utilities.py
pulumi_databricks/access_control_rule_set.py
pulumi_databricks/account_federation_policy.py
pulumi_databricks/account_network_policy.py
pulumi_databricks/account_setting_v2.py
pulumi_databricks/aibi_dashboard_embedding_access_policy_setting.py
pulumi_databricks/aibi_dashboard_embedding_approved_domains_setting.py
pulumi_databricks/alert.py
pulumi_databricks/alert_v2.py
pulumi_databricks/app.py
pulumi_databricks/apps_settings_custom_template.py
pulumi_databricks/artifact_allowlist.py
pulumi_databricks/automatic_cluster_update_workspace_setting.py
pulumi_databricks/budget.py
pulumi_databricks/budget_policy.py
pulumi_databricks/catalog.py
pulumi_databricks/catalog_workspace_binding.py
pulumi_databricks/cluster.py
pulumi_databricks/cluster_policy.py
pulumi_databricks/compliance_security_profile_workspace_setting.py
pulumi_databricks/connection.py
pulumi_databricks/credential.py
pulumi_databricks/custom_app_integration.py
pulumi_databricks/dashboard.py
pulumi_databricks/data_quality_monitor.py
pulumi_databricks/data_quality_refresh.py
pulumi_databricks/database_database_catalog.py
pulumi_databricks/database_instance.py
pulumi_databricks/database_synced_database_table.py
pulumi_databricks/dbfs_file.py
pulumi_databricks/default_namespace_setting.py
pulumi_databricks/directory.py
pulumi_databricks/disable_legacy_access_setting.py
pulumi_databricks/disable_legacy_dbfs_setting.py
pulumi_databricks/disable_legacy_features_setting.py
pulumi_databricks/enhanced_security_monitoring_workspace_setting.py
pulumi_databricks/entitlements.py
pulumi_databricks/entity_tag_assignment.py
pulumi_databricks/external_location.py
pulumi_databricks/external_metadata.py
pulumi_databricks/feature_engineering_feature.py
pulumi_databricks/feature_engineering_materialized_feature.py
pulumi_databricks/file.py
pulumi_databricks/get_account_federation_policies.py
pulumi_databricks-1.78.0.dist-info/METADATA
pulumi_databricks-1.78.0.dist-info/WHEEL
pulumi_databricks-1.78.0.dist-info/top_level.txt
pulumi_databricks-1.78.0.dist-info/RECORD
